Metadata-Version: 2.1
Name: PanACoTA
Version: 1.3.0
Summary: Large scale comparative genomics tools: annotate genomes, do pangenome, core/persistent genome, align core/persistent families, infer phylogenetic tree.
Home-page: https://github.com/gem-pasteur/PanACoTA
Author: Amandine Perrin
Author-email: amandine.perrin@pasteur.fr
License: AGPL v3
Platform: OS Independent
Classifier: Environment :: Console
Classifier: Intended Audience :: Science/Research
Classifier: License :: OSI Approved :: GNU Affero General Public License v3
Classifier: Programming Language :: Python :: 3
Classifier: Operating System :: OS Independent
Classifier: Topic :: Scientific/Engineering :: Bio-Informatics
Requires-Python: >=3.4
Provides-Extra: dev
